{
    "pipes": [],
    "interfaces": [],
    "injectables": [],
    "classes": [
        {
            "name": "AppPage",
            "id": "class-AppPage-ee2067dfb1c303f41003aea7d82d51e0",
            "file": "e2e/src/app.po.ts",
            "type": "class",
            "sourceCode": "import { browser, by, element } from 'protractor';\n\nexport class AppPage {\n  async navigateTo(): Promise<unknown> {\n    return browser.get(browser.baseUrl);\n  }\n\n  async getTitleText(): Promise<string> {\n    return element(by.css('app-root .content span')).getText();\n  }\n}\n",
            "properties": [],
            "methods": [
                {
                    "name": "getTitleText",
                    "args": [],
                    "optional": false,
                    "returnType": "Promise<string>",
                    "typeParameters": [],
                    "line": 8,
                    "modifierKind": [
                        120
                    ]
                },
                {
                    "name": "navigateTo",
                    "args": [],
                    "optional": false,
                    "returnType": "Promise<unknown>",
                    "typeParameters": [],
                    "line": 4,
                    "modifierKind": [
                        120
                    ]
                }
            ],
            "indexSignatures": [],
            "inputsClass": [],
            "outputsClass": [],
            "hostBindings": [],
            "hostListeners": []
        }
    ],
    "directives": [],
    "components": [
        {
            "name": "AppComponent",
            "id": "component-AppComponent-f5d0d2acde18df6dadb311ec70ee3546",
            "file": "src/app/app.component.ts",
            "encapsulation": [],
            "entryComponents": [],
            "inputs": [],
            "outputs": [],
            "providers": [],
            "selector": "app-root",
            "styleUrls": [],
            "styles": [],
            "template": "  <!-- This example requires Tailwind CSS v2.0+ -->\n<div class=\"bg-gray-50\">\n  <div class=\"max-w-7xl mx-auto py-12 px-4 sm:px-6 lg:py-16 lg:px-8 lg:flex lg:items-center lg:justify-between\">\n    <h2 class=\"text-3xl font-extrabold tracking-tight text-gray-900 sm:text-4xl\">\n      <span class=\"block\">Ready to dive in?</span>\n      <span class=\"block text-indigo-600\">Start your free trial today.</span>\n    </h2>\n    <div class=\"mt-8 flex lg:mt-0 lg:flex-shrink-0\">\n      <div class=\"inline-flex rounded-md shadow\">\n        <a href=\"#\" class=\"inline-flex items-center justify-center px-5 py-3 border border-transparent text-base font-medium rounded-md text-white bg-indigo-600 hover:bg-indigo-700\">\n          Get started\n        </a>\n      </div>\n      <div class=\"ml-3 inline-flex rounded-md shadow\">\n        <a href=\"#\" class=\"inline-flex items-center justify-center px-5 py-3 border border-transparent text-base font-medium rounded-md text-indigo-600 bg-white hover:bg-indigo-50\">\n          Learn more\n        </a>\n      </div>\n    </div>\n  </div>\n</div>\n",
            "templateUrl": [],
            "viewProviders": [],
            "inputsClass": [],
            "outputsClass": [],
            "propertiesClass": [
                {
                    "name": "title",
                    "defaultValue": "'wyhh-web'",
                    "type": "string",
                    "optional": false,
                    "description": "",
                    "line": 30
                }
            ],
            "methodsClass": [],
            "hostBindings": [],
            "hostListeners": [],
            "description": "",
            "rawdescription": "",
            "type": "component",
            "sourceCode": "import { Component } from '@angular/core';\n\n@Component({\n  selector: 'app-root',\n  template: `\n  <!-- This example requires Tailwind CSS v2.0+ -->\n<div class=\"bg-gray-50\">\n  <div class=\"max-w-7xl mx-auto py-12 px-4 sm:px-6 lg:py-16 lg:px-8 lg:flex lg:items-center lg:justify-between\">\n    <h2 class=\"text-3xl font-extrabold tracking-tight text-gray-900 sm:text-4xl\">\n      <span class=\"block\">Ready to dive in?</span>\n      <span class=\"block text-indigo-600\">Start your free trial today.</span>\n    </h2>\n    <div class=\"mt-8 flex lg:mt-0 lg:flex-shrink-0\">\n      <div class=\"inline-flex rounded-md shadow\">\n        <a href=\"#\" class=\"inline-flex items-center justify-center px-5 py-3 border border-transparent text-base font-medium rounded-md text-white bg-indigo-600 hover:bg-indigo-700\">\n          Get started\n        </a>\n      </div>\n      <div class=\"ml-3 inline-flex rounded-md shadow\">\n        <a href=\"#\" class=\"inline-flex items-center justify-center px-5 py-3 border border-transparent text-base font-medium rounded-md text-indigo-600 bg-white hover:bg-indigo-50\">\n          Learn more\n        </a>\n      </div>\n    </div>\n  </div>\n</div>\n`\n})\nexport class AppComponent {\n  title = 'wyhh-web';\n}\n",
            "assetsDirs": [],
            "styleUrlsData": "",
            "stylesData": ""
        }
    ],
    "modules": [
        {
            "name": "AppModule",
            "children": [
                {
                    "type": "providers",
                    "elements": []
                },
                {
                    "type": "declarations",
                    "elements": [
                        {
                            "name": "AppComponent"
                        }
                    ]
                },
                {
                    "type": "imports",
                    "elements": [
                        {
                            "name": "AppRoutingModule"
                        }
                    ]
                },
                {
                    "type": "exports",
                    "elements": []
                },
                {
                    "type": "bootstrap",
                    "elements": [
                        {
                            "name": "AppComponent"
                        }
                    ]
                },
                {
                    "type": "classes",
                    "elements": []
                }
            ]
        },
        {
            "name": "AppRoutingModule",
            "children": [
                {
                    "type": "providers",
                    "elements": []
                },
                {
                    "type": "declarations",
                    "elements": []
                },
                {
                    "type": "imports",
                    "elements": []
                },
                {
                    "type": "exports",
                    "elements": []
                },
                {
                    "type": "bootstrap",
                    "elements": []
                },
                {
                    "type": "classes",
                    "elements": []
                }
            ]
        }
    ],
    "miscellaneous": {
        "variables": [
            {
                "name": "context",
                "ctype": "miscellaneous",
                "subtype": "variable",
                "file": "src/test.ts",
                "type": "",
                "defaultValue": "require.context('./', true, /\\.spec\\.ts$/)"
            },
            {
                "name": "environment",
                "ctype": "miscellaneous",
                "subtype": "variable",
                "file": "src/environments/environment.prod.ts",
                "type": "object",
                "defaultValue": "{\n  production: true\n}"
            },
            {
                "name": "environment",
                "ctype": "miscellaneous",
                "subtype": "variable",
                "file": "src/environments/environment.ts",
                "type": "object",
                "defaultValue": "{\n  production: false\n}"
            },
            {
                "name": "require",
                "ctype": "miscellaneous",
                "subtype": "variable",
                "file": "src/test.ts",
                "type": "literal type"
            }
        ],
        "functions": [],
        "typealiases": [],
        "enumerations": [],
        "groupedVariables": {
            "src/test.ts": [
                {
                    "name": "context",
                    "ctype": "miscellaneous",
                    "subtype": "variable",
                    "file": "src/test.ts",
                    "type": "",
                    "defaultValue": "require.context('./', true, /\\.spec\\.ts$/)"
                },
                {
                    "name": "require",
                    "ctype": "miscellaneous",
                    "subtype": "variable",
                    "file": "src/test.ts",
                    "type": "literal type"
                }
            ],
            "src/environments/environment.prod.ts": [
                {
                    "name": "environment",
                    "ctype": "miscellaneous",
                    "subtype": "variable",
                    "file": "src/environments/environment.prod.ts",
                    "type": "object",
                    "defaultValue": "{\n  production: true\n}"
                }
            ],
            "src/environments/environment.ts": [
                {
                    "name": "environment",
                    "ctype": "miscellaneous",
                    "subtype": "variable",
                    "file": "src/environments/environment.ts",
                    "type": "object",
                    "defaultValue": "{\n  production: false\n}"
                }
            ]
        },
        "groupedFunctions": {},
        "groupedEnumerations": {},
        "groupedTypeAliases": {}
    },
    "routes": {
        "name": "<root>",
        "kind": "module",
        "className": "AppModule",
        "children": [
            {
                "name": "routes",
                "filename": "src/app/app-routing.module.ts",
                "module": "AppRoutingModule",
                "children": [],
                "kind": "module"
            }
        ]
    },
    "coverage": {
        "count": 0,
        "status": "low",
        "files": [
            {
                "filePath": "e2e/src/app.po.ts",
                "type": "class",
                "linktype": "classe",
                "name": "AppPage",
                "coveragePercent": 0,
                "coverageCount": "0/3",
                "status": "low"
            },
            {
                "filePath": "src/app/app.component.ts",
                "type": "component",
                "linktype": "component",
                "name": "AppComponent",
                "coveragePercent": 0,
                "coverageCount": "0/2",
                "status": "low"
            },
            {
                "filePath": "src/environments/environment.prod.ts",
                "type": "variable",
                "linktype": "miscellaneous",
                "linksubtype": "variable",
                "name": "environment",
                "coveragePercent": 0,
                "coverageCount": "0/1",
                "status": "low"
            },
            {
                "filePath": "src/environments/environment.ts",
                "type": "variable",
                "linktype": "miscellaneous",
                "linksubtype": "variable",
                "name": "environment",
                "coveragePercent": 0,
                "coverageCount": "0/1",
                "status": "low"
            },
            {
                "filePath": "src/test.ts",
                "type": "variable",
                "linktype": "miscellaneous",
                "linksubtype": "variable",
                "name": "context",
                "coveragePercent": 0,
                "coverageCount": "0/1",
                "status": "low"
            },
            {
                "filePath": "src/test.ts",
                "type": "variable",
                "linktype": "miscellaneous",
                "linksubtype": "variable",
                "name": "require",
                "coveragePercent": 0,
                "coverageCount": "0/1",
                "status": "low"
            }
        ]
    }
}